{
    "local_business": [{
        "name": "Notaria Paino",
        "description": "Notary Office",
        "address": {
            "street": "Aramburu Avenue",
            "number": 668,
            "district": "Surquillo",
            "postal_code": "Lima 34"
        },
        "url": "https://www.notariapaino.com.pe/",
        "contact": {
            "phone": 5116185151,
            "email": "info@notariapaino.com.pe"
        },
        "image": "notaria-paino.jpg"
    }, {
        "name": "Rodrigo, Elias & Medrano",
        "description": "Law Firm",
        "address": {
            "street": "San Felipe Avenue",
            "number": 758,
            "district": "Jesus Maria",
            "postal_code": "Lima 15072"
        },
        "url": "https://www.estudiorodrigo.com/",
        "contact": {
            "phone": 5116191900,
            "email": "contacto@estudiorodrigo.com"
        },
        "image": "estudio-rodrigo.jpg"
    }, {
        "name": "Anita",
        "description": "Exchange Shop",
        "address": {
            "street": "Primavera Avenue",
            "number": 282,
            "district": "Santiago de Surco",
            "postal_code": "Lima 33"
        },
        "url": "http://www.casadecambioanita.com/",
        "contact": {
            "phone": 5113724006,
            "email": "casadecambioanita@gmail.com"
        },
        "image": "casa-anita.jpg"
    }, {
        "name": "Country Club El Bosque",
        "description": "Relax Club",
        "address": {
            "street": "Julio Bayletti Avenue",
            "number": 278,
            "district": "San Borja",
            "postal_code": "Lima 34"
        },
        "url": "http://www.elbosque.org.pe/",
        "contact": {
            "phone": 5112070670,
            "email": "contacto@elbosque.org.pe"
        },
        "image": "el-bosque.jpg"
    }, {
        "name": "XSport Gym",
        "description": "Fitness Club",
        "address": {
            "street": "Santiago de Surco Avenue",
            "number": 3115,
            "district": "Santiago de Surco",
            "postal_code": "Lima 33"
        },
        "url": "https://www.xsportgym.pe/",
        "contact": {
            "phone": 5112603364,
            "email": "info@xsportgym.pe"
        },
        "image": "xsport-gym.jpg"
    }, {
        "name": "Mirabus",
        "description": "City Tour",
        "address": {
            "street": "Martir Jose Olaya Street",
            "number": 100,
            "district": "Miraflores",
            "postal_code": "Lima 25"
        },
        "url": "https://www.mirabusperu.com/",
        "contact": {
            "phone": 5112426699,
            "email": "info@mirabus.com"
        },
        "image": "mirabus.jpg"
    }, {
        "name": "Avis",
        "description": "Car Rental",
        "address": {
            "street": "Las Begonias Street",
            "number": 385,
            "district": "San Isidro",
            "postal_code": "Lima 29"
        },
        "url": "https://www.avis.com/en/locations/pe/lima",
        "contact": {
            "phone": 5112076000,
            "email": "lima@avis.com"
        },
        "image": "avis.jpg"
    }],
    "events": [{
        "name": "Lima Anniversary",
        "date": "January 18th",
        "place": "Plaza Mayor",
        "image": "lima-anniversary.jpg"
    }, {
        "name": "Militar Parade",
        "date": "July 29th",
        "place": "Brasil Avenue",
        "image": "militar-parade.jpg"
    }, {
        "name": "Mistura Food Festival",
        "date": "September 10th",
        "place": "Costa Verde Magdalena",
        "image": "mistura-festival.jpg"
    }],
    "gallery": [{
        "title": "San Isidro, financial district",
        "image": "image1.jpg"
    }, {
        "title": "Lima Cathedral",
        "image": "image2.jpg"
    }, {
        "title": "Water Park",
        "image": "image3.jpg"
    }, {
        "title": "Plaza Mayor",
        "image": "image4.jpg"
    }, {
        "title": "Miaflores Beacon",
        "image": "image5.jpg"
    }, {
        "title": "Costa Verde, Miraflores",
        "image": "image6.jpg"
    }],
    "directors": [{
        "name": "Pamela Pérez",
        "position": "CEO Founder",
        "contact": "perezvp@limabusiness.info",
        "image": "perezvp-profile.jpg"
    }, {
        "name": "Julián Camino",
        "position": "Operations Manager",
        "contact": "caminojg@limabusiness.info",
        "image": "caminojg-profile.jpg"
    }, {
        "name": "Fabiola Manrique",
        "position": "Customer Service Manager",
        "contact": "manriquefx@limabusiness.info",
        "image": "manriquefx-profile.jpg"
    }, {
        "name": "Sebastián Quisiyupanqui",
        "position": "Community Manager",
        "contact": "quisiyupanquisx@limabusiness.info",
        "image": "quisiyupanquisx-profile.jpg"
    }]
}